[
    {
        "key": "datr",
        "value": "ejRLaM6kD9OPZYe94dePlx1U",
        "domain": "facebook.com",
        "path": "/",
        "hostOnly": false,
        "creation": "2025-06-15T10:18:25.396Z",
        "lastAccessed": "2025-06-15T10:18:25.397Z"
    },
    {
        "key": "sb",
        "value": "ejRLaBoP9eDGpyBPk9Id-YjX",
        "domain": "facebook.com",
        "path": "/",
        "hostOnly": false,
        "creation": "2025-06-15T10:18:25.397Z",
        "lastAccessed": "2025-06-15T10:18:25.397Z"
    },
    {
        "key": "locale",
        "value": "as_IN",
        "domain": "facebook.com",
        "path": "/",
        "hostOnly": false,
        "creation": "2025-06-15T10:18:25.397Z",
        "lastAccessed": "2025-06-15T10:18:25.397Z"
    },
    {
        "key": "vpd",
        "value": "v1%3B772x393x2.75",
        "domain": "facebook.com",
        "path": "/",
        "hostOnly": false,
        "creation": "2025-06-15T10:18:25.397Z",
        "lastAccessed": "2025-06-15T10:18:25.397Z"
    },
    {
        "key": "ps_l",
        "value": "1",
        "domain": "facebook.com",
        "path": "/",
        "hostOnly": false,
        "creation": "2025-06-15T10:18:25.397Z",
        "lastAccessed": "2025-06-15T10:18:25.397Z"
    },
    {
        "key": "ps_n",
        "value": "1",
        "domain": "facebook.com",
        "path": "/",
        "hostOnly": false,
        "creation": "2025-06-15T10:18:25.397Z",
        "lastAccessed": "2025-06-15T10:18:25.397Z"
    },
    {
        "key": "c_user",
        "value": "100032199712152",
        "domain": "facebook.com",
        "path": "/",
        "hostOnly": false,
        "creation": "2025-06-15T10:18:25.397Z",
        "lastAccessed": "2025-06-15T10:18:25.397Z"
    },
    {
        "key": "xs",
        "value": "43%3AikXZxN31WRdw6g%3A2%3A1749957469%3A-1%3A-1",
        "domain": "facebook.com",
        "path": "/",
        "hostOnly": false,
        "creation": "2025-06-15T10:18:25.397Z",
        "lastAccessed": "2025-06-15T10:18:25.397Z"
    },
    {
        "key": "fr",
        "value": "0skJRmnajrRBUV2Pj.AWc0NPraPZEgsb7n0MMU6AsRpzLDxJ-EW-qNHuTLK1b4L5HWfQE.BoSzR6..AAA.0.0.BoTp3k.AWcvfvAljrtDDf4IVPdEvYG5Yvk",
        "domain": "facebook.com",
        "path": "/",
        "hostOnly": false,
        "creation": "2025-06-15T10:18:25.397Z",
        "lastAccessed": "2025-06-15T10:18:25.397Z"
    },
    {
        "key": "fbl_st",
        "value": "100436984%3BT%3A29166378",
        "domain": "facebook.com",
        "path": "/",
        "hostOnly": false,
        "creation": "2025-06-15T10:18:25.397Z",
        "lastAccessed": "2025-06-15T10:18:25.397Z"
    },
    {
        "key": "wl_cbv",
        "value": "v2%3Bclient_version%3A2844%3Btimestamp%3A1749982692",
        "domain": "facebook.com",
        "path": "/",
        "hostOnly": false,
        "creation": "2025-06-15T10:18:25.397Z",
        "lastAccessed": "2025-06-15T10:18:25.397Z"
    }
]
